syllable_reading/__init__.py
syllable_reading/cli.py
syllable_reading/syllable_reading.py
syllable_reading-0.1.1.dist-info/AUTHORS.rst
syllable_reading-0.1.1.dist-info/LICENSE
syllable_reading-0.1.1.dist-info/METADATA
syllable_reading-0.1.1.dist-info/WHEEL
syllable_reading-0.1.1.dist-info/entry_points.txt
syllable_reading-0.1.1.dist-info/top_level.txt
syllable_reading-0.1.1.dist-info/RECORD
