Metadata-Version: 2.1
Name: syllable-reading
Version: 0.1.1
Summary: Pgenerate bold text divided by syllables
Home-page: https://github.com/idlepig/syllable_reading
Author: idlepig
Author-email: newellzhou@163.com
License: MIT license
Keywords: syllable_reading
Platform: UNKNOWN
Classifier: Development Status :: 2 - Pre-Alpha
Classifier: Intended Audience :: Developers
Classifier: License :: OSI Approved :: MIT License
Classifier: Natural Language :: English
Classifier: Programming Language :: Python :: 3
Classifier: Programming Language :: Python :: 3.6
Classifier: Programming Language :: Python :: 3.7
Classifier: Programming Language :: Python :: 3.8
Requires-Python: >=3.6
License-File: LICENSE
License-File: AUTHORS.rst
